checkandconvert/check.py
checkandconvert/convert.py
checkandconvert-0.1.0.dist-info/METADATA
checkandconvert-0.1.0.dist-info/WHEEL
checkandconvert-0.1.0.dist-info/top_level.txt
checkandconvert-0.1.0.dist-info/RECORD
