Metadata-Version: 2.1
Name: checkandconvert
Version: 0.1.0
Summary: A simple package to both check the four main types of a Series (int, float, bool, and str), and convert to these types
Home-page: UNKNOWN
Author: UNKNOWN
Author-email: UNKNOWN
License: MIT
Platform: UNKNOWN
